text_analyzer/__init__.py
text_analyzer/bad_arguments_provided_exception.py
text_analyzer/constants.py
text_analyzer/db.py
text_analyzer/db_utils.py
text_analyzer/file_utils.py
text_analyzer/flag_scripts.py
text_analyzer/launcher.py
text_analyzer/main.py
text_analyzer/model.py
text_analyzer/printers.py
text_analyzer/reports/__init__.py
text_analyzer/reports/characters_report.py
text_analyzer/reports/palindrome_report.py
text_analyzer/reports/sentences_report.py
text_analyzer/reports/words_report.py
text_analyzer_DENYS_IVANENKO-0.0.1.dist-info/LICENSE
text_analyzer_DENYS_IVANENKO-0.0.1.dist-info/METADATA
text_analyzer_DENYS_IVANENKO-0.0.1.dist-info/WHEEL
text_analyzer_DENYS_IVANENKO-0.0.1.dist-info/top_level.txt
text_analyzer_DENYS_IVANENKO-0.0.1.dist-info/RECORD
