Metadata-Version: 2.1
Name: text-analyzer-DENYS-IVANENKO
Version: 0.0.1
Summary: Text Analyzer
Home-page: https://git.epam.com/denys_ivanenko/advancedpython1hw
Author: Denys Ivanenko
Author-email: denys_ivanenko@epam.com
License: UNKNOWN
Project-URL: Bug Tracker, https://github.com/pypa/sampleproject/issues
Platform: UNKNOWN
Classifier: Programming Language :: Python :: 3
Classifier: License :: OSI Approved :: MIT License
Classifier: Operating System :: OS Independent
Requires-Python: >=3.9
License-File: LICENSE
